<?xml version="1.0" encoding="utf-8"?>
<item xmlns="http://www.gamned.org/bear/schema/0.5" xmlns:xsi="http://www.w3.org/2001/XMLSchema-instance" xsi:schemaLocation="http://www.gamned.org/bear/schema/0.5 http://www.gamned.org/bear/schema/0.5/item-description.xsd" class="ptb::level_settings" category="settings" fixable="false" box_color="#D48E82" url="http://www.gamned.org/wiki/index.php/level_settings">
  <inherit>
    <class>bear::level_settings</class>
  </inherit>
  <description>An item to set parameters of level.</description>
  <fields>
    <field type="boolean" name="level_settings.is_main_level">
      <description>Indicates if the level is a main level.</description>
      <default_value>true</default_value>
    </field>
    <field type="boolean" name="level_settings.friendly_fire">
      <description>Indicates if players can harm each other.</description>
      <default_value>unmodified</default_value>
    </field>
    <field type="boolean" name="level_settings.game_over_allowed">
      <description>Indicates if game over is allowed.</description>
      <default_value>true</default_value>
    </field>
    <field type="boolean" name="level_settings.player_status_fixed">
      <description>Indicates if player status are fixed.</description>
      <default_value>false</default_value>
    </field>
  </fields>
</item>
