<?xml version="1.0" encoding="utf-8"?>
<item xmlns="http://www.gamned.org/bear/schema/0.5" xmlns:xsi="http://www.w3.org/2001/XMLSchema-instance" xsi:schemaLocation="http://www.gamned.org/bear/schema/0.5 http://www.gamned.org/bear/schema/0.5/item-description.xsd" class="ptb::rolling_ball" category="enemy/castle" box_color="#98F74E" url="http://www.gamned.org/wiki/index.php/rolling_ball">
  <inherit>
    <class>ptb::passive_enemy</class>
  </inherit>
  <description>The class describing a rolling ball.</description>

  <new_default_value name="base_item.free_system">true</new_default_value>
</item>
